libfreehackquestclient/__init__.py
libfreehackquestclient/freehackquest_api_leaks.py
libfreehackquestclient/freehackquest_client.py
libfreehackquestclient-0.2.36.dist-info/LICENSE
libfreehackquestclient-0.2.36.dist-info/METADATA
libfreehackquestclient-0.2.36.dist-info/WHEEL
libfreehackquestclient-0.2.36.dist-info/top_level.txt
libfreehackquestclient-0.2.36.dist-info/RECORD
