Metadata-Version: 2.1
Name: libfreehackquestclient
Version: 0.2.36
Summary: FreeHackQuest Python Client Library for fhq-server
Home-page: https://github.com/freehackquest/libfreehackquest-client-py
Author: FreeHackQuest Team
Author-email: freehackquest@gmail.com
License: UNKNOWN
Keywords: ctf,fhq,fhq-server,libfreehackquest-client,jeopardy,freehackquest
Platform: UNKNOWN
Classifier: Programming Language :: Python :: 3
Classifier: License :: OSI Approved :: Apache Software License
Classifier: Operating System :: OS Independent
Requires-Python: >=3.6
Requires-Dist: requests (>=2.21.0)
Requires-Dist: websocket-client (>=0.56.0)
